sborf/explain.py
sborf/optimize.py
sborf/predict.py
sborf/sborf_standalone.py
sborf/models/cerevisiae/probabilityScaler.m
sborf/models/cerevisiae/stateDiz.m
sborf/models/coli/probabilityScaler.m
sborf/models/coli/stateDiz.m
sborf/models/musculus/probabilityScaler.m
sborf/models/musculus/stateDiz.m
sborf/src/NNWrappers.py
sborf/src/dna_features.py
sborf/src/model_old.py
sborf/src/parse.py
sborf/src/protein2dna.py
sborf/src/utils.py
sborf/src/writeExplaination.py
sborf-0.0.3.dist-info/METADATA
sborf-0.0.3.dist-info/WHEEL
sborf-0.0.3.dist-info/entry_points.txt
sborf-0.0.3.dist-info/top_level.txt
sborf-0.0.3.dist-info/RECORD
