Metadata-Version: 2.4
Name: sborf
Version: 0.0.3
Summary: A neural network that predicts and designs alternative DNA encodings for proteins, aiming to fine-tune their expression
Home-page: https://github.com/grogdrinker/sborf
Author: Gabriele Orlando
Author-email: orlando.gabriele89@gmail.com
Classifier: Programming Language :: Python :: 3
Classifier: Operating System :: OS Independent
Requires-Dist: torch
Requires-Dist: numpy
Requires-Dist: scikit-learn
Dynamic: author
Dynamic: author-email
Dynamic: classifier
Dynamic: description
Dynamic: description-content-type
Dynamic: home-page
Dynamic: requires-dist
Dynamic: summary
